[
  {
    "quest_id": "q_main_001",
    "quest_type": "main",
    "name_ko": "초심 수련의 길",
    "world": "mortal",
    "recommended_difficulty_min": "1",
    "recommended_difficulty_max": "6",
    "objective_type": "clear_node",
    "objective_value": "node_m_001",
    "reward_primary_type": "currency_spirit_coin",
    "reward_primary_value": "300",
    "reward_secondary_type": "resource_qi",
    "reward_secondary_value": "1200",
    "reward_item_ref": "pot_qi_01",
    "repeatable": "no",
    "unlock_condition": "difficulty>=1",
    "note": "튜토리얼 메인"
  },
  {
    "quest_id": "q_main_002",
    "quest_type": "main",
    "name_ko": "첫 정예 토벌",
    "world": "mortal",
    "recommended_difficulty_min": "6",
    "recommended_difficulty_max": "14",
    "objective_type": "kill_elite",
    "objective_value": "3",
    "reward_primary_type": "currency_spirit_coin",
    "reward_primary_value": "600",
    "reward_secondary_type": "resource_qi",
    "reward_secondary_value": "1800",
    "reward_item_ref": "pot_brk_01",
    "repeatable": "no",
    "unlock_condition": "difficulty>=6",
    "note": "정예 입문"
  },
  {
    "quest_id": "q_main_003",
    "quest_type": "main",
    "name_ko": "연기의 정점",
    "world": "mortal",
    "recommended_difficulty_min": "10",
    "recommended_difficulty_max": "18",
    "objective_type": "reach_difficulty",
    "objective_value": "13",
    "reward_primary_type": "currency_spirit_coin",
    "reward_primary_value": "900",
    "reward_secondary_type": "currency_rebirth_essence",
    "reward_secondary_value": "3",
    "reward_item_ref": "tal_qi_01",
    "repeatable": "no",
    "unlock_condition": "difficulty>=10",
    "note": "연기 대원만"
  },
  {
    "quest_id": "q_main_004",
    "quest_type": "main",
    "name_ko": "황혼 고도 정리",
    "world": "mortal",
    "recommended_difficulty_min": "20",
    "recommended_difficulty_max": "32",
    "objective_type": "clear_zone",
    "objective_value": "m_zone_02",
    "reward_primary_type": "currency_spirit_coin",
    "reward_primary_value": "1500",
    "reward_secondary_type": "resource_qi",
    "reward_secondary_value": "3200",
    "reward_item_ref": "pot_brk_02",
    "repeatable": "no",
    "unlock_condition": "difficulty>=20",
    "note": "중반 메인"
  },
  {
    "quest_id": "q_main_005",
    "quest_type": "main",
    "name_ko": "요수림 정화",
    "world": "mortal",
    "recommended_difficulty_min": "34",
    "recommended_difficulty_max": "48",
    "objective_type": "kill_monster",
    "objective_value": "mob_m_007:20",
    "reward_primary_type": "currency_spirit_coin",
    "reward_primary_value": "1800",
    "reward_secondary_type": "currency_rebirth_essence",
    "reward_secondary_value": "6",
    "reward_item_ref": "pot_def_01",
    "repeatable": "no",
    "unlock_condition": "difficulty>=34",
    "note": "독 몹 구간"
  },
  {
    "quest_id": "q_main_006",
    "quest_type": "main",
    "name_ko": "천뢰협곡 돌파",
    "world": "mortal",
    "recommended_difficulty_min": "64",
    "recommended_difficulty_max": "80",
    "objective_type": "clear_zone",
    "objective_value": "m_zone_05",
    "reward_primary_type": "currency_spirit_coin",
    "reward_primary_value": "2600",
    "reward_secondary_type": "currency_rebirth_essence",
    "reward_secondary_value": "10",
    "reward_item_ref": "pot_tri_02",
    "repeatable": "no",
    "unlock_condition": "difficulty>=64",
    "note": "후반 메인"
  },
  {
    "quest_id": "q_main_007",
    "quest_type": "main",
    "name_ko": "인간계 도겁 준비",
    "world": "mortal",
    "recommended_difficulty_min": "84",
    "recommended_difficulty_max": "96",
    "objective_type": "consume_item",
    "objective_value": "pot_tri_02:2",
    "reward_primary_type": "currency_spirit_coin",
    "reward_primary_value": "3000",
    "reward_secondary_type": "currency_rebirth_essence",
    "reward_secondary_value": "18",
    "reward_item_ref": "tal_guard_02",
    "repeatable": "no",
    "unlock_condition": "difficulty>=84",
    "note": "도겁 준비선"
  },
  {
    "quest_id": "q_main_008",
    "quest_type": "main",
    "name_ko": "운해선원 입문",
    "world": "immortal",
    "recommended_difficulty_min": "105",
    "recommended_difficulty_max": "116",
    "objective_type": "clear_node",
    "objective_value": "node_i_001",
    "reward_primary_type": "currency_spirit_coin",
    "reward_primary_value": "4200",
    "reward_secondary_type": "resource_qi",
    "reward_secondary_value": "6200",
    "reward_item_ref": "pot_def_03",
    "repeatable": "no",
    "unlock_condition": "difficulty>=105",
    "note": "신선계 진입"
  },
  {
    "quest_id": "q_main_009",
    "quest_type": "main",
    "name_ko": "적화비경 격파",
    "world": "immortal",
    "recommended_difficulty_min": "120",
    "recommended_difficulty_max": "136",
    "objective_type": "kill_boss",
    "objective_value": "node_i_006",
    "reward_primary_type": "currency_spirit_coin",
    "reward_primary_value": "5600",
    "reward_secondary_type": "currency_rebirth_essence",
    "reward_secondary_value": "30",
    "reward_item_ref": "pot_tri_03",
    "repeatable": "no",
    "unlock_condition": "difficulty>=120",
    "note": "신선계 중반"
  },
  {
    "quest_id": "q_main_010",
    "quest_type": "main",
    "name_ko": "신선계 도겁 관문",
    "world": "immortal",
    "recommended_difficulty_min": "166",
    "recommended_difficulty_max": "182",
    "objective_type": "clear_node",
    "objective_value": "node_i_012",
    "reward_primary_type": "currency_spirit_coin",
    "reward_primary_value": "8000",
    "reward_secondary_type": "currency_rebirth_essence",
    "reward_secondary_value": "55",
    "reward_item_ref": "tal_luck_02",
    "repeatable": "no",
    "unlock_condition": "difficulty>=166",
    "note": "신선계 종결"
  },
  {
    "quest_id": "q_main_011",
    "quest_type": "main",
    "name_ko": "원초계단 생환",
    "world": "true",
    "recommended_difficulty_min": "183",
    "recommended_difficulty_max": "190",
    "objective_type": "clear_zone",
    "objective_value": "t_zone_01",
    "reward_primary_type": "currency_spirit_coin",
    "reward_primary_value": "12000",
    "reward_secondary_type": "currency_rebirth_essence",
    "reward_secondary_value": "95",
    "reward_item_ref": "pot_tri_03",
    "repeatable": "no",
    "unlock_condition": "difficulty>=183",
    "note": "진선계 입문"
  },
  {
    "quest_id": "q_main_012",
    "quest_type": "main",
    "name_ko": "원조심연 최종전",
    "world": "true",
    "recommended_difficulty_min": "194",
    "recommended_difficulty_max": "198",
    "objective_type": "kill_boss",
    "objective_value": "node_t_012",
    "reward_primary_type": "currency_spirit_coin",
    "reward_primary_value": "18000",
    "reward_secondary_type": "currency_rebirth_essence",
    "reward_secondary_value": "180",
    "reward_item_ref": "tal_luck_02",
    "repeatable": "no",
    "unlock_condition": "difficulty>=194",
    "note": "최종 메인"
  },
  {
    "quest_id": "q_daily_001",
    "quest_type": "daily",
    "name_ko": "오늘의 수련",
    "world": "daily",
    "recommended_difficulty_min": "1",
    "recommended_difficulty_max": "198",
    "objective_type": "gain_qi",
    "objective_value": "15000",
    "reward_primary_type": "currency_spirit_coin",
    "reward_primary_value": "500",
    "reward_secondary_type": "currency_rebirth_essence",
    "reward_secondary_value": "2",
    "reward_item_ref": "none",
    "repeatable": "yes",
    "unlock_condition": "difficulty>=1",
    "note": "일일 기본"
  },
  {
    "quest_id": "q_daily_002",
    "quest_type": "daily",
    "name_ko": "일일 정예 토벌",
    "world": "daily",
    "recommended_difficulty_min": "10",
    "recommended_difficulty_max": "198",
    "objective_type": "kill_elite",
    "objective_value": "6",
    "reward_primary_type": "currency_spirit_coin",
    "reward_primary_value": "900",
    "reward_secondary_type": "currency_rebirth_essence",
    "reward_secondary_value": "4",
    "reward_item_ref": "pot_brk_01",
    "repeatable": "yes",
    "unlock_condition": "difficulty>=10",
    "note": "일일 전투"
  },
  {
    "quest_id": "q_daily_003",
    "quest_type": "daily",
    "name_ko": "일일 보스 도전",
    "world": "daily",
    "recommended_difficulty_min": "32",
    "recommended_difficulty_max": "198",
    "objective_type": "kill_boss",
    "objective_value": "2",
    "reward_primary_type": "currency_spirit_coin",
    "reward_primary_value": "1200",
    "reward_secondary_type": "currency_rebirth_essence",
    "reward_secondary_value": "7",
    "reward_item_ref": "pot_def_02",
    "repeatable": "yes",
    "unlock_condition": "difficulty>=32",
    "note": "일일 보스"
  },
  {
    "quest_id": "q_daily_004",
    "quest_type": "daily",
    "name_ko": "도겁 대비 훈련",
    "world": "daily",
    "recommended_difficulty_min": "70",
    "recommended_difficulty_max": "198",
    "objective_type": "clear_tribulation_sim",
    "objective_value": "1",
    "reward_primary_type": "currency_spirit_coin",
    "reward_primary_value": "1500",
    "reward_secondary_type": "currency_rebirth_essence",
    "reward_secondary_value": "10",
    "reward_item_ref": "pot_tri_02",
    "repeatable": "yes",
    "unlock_condition": "difficulty>=70",
    "note": "도겁 모의전"
  },
  {
    "quest_id": "q_daily_005",
    "quest_type": "daily",
    "name_ko": "연금 재료 수집",
    "world": "daily",
    "recommended_difficulty_min": "18",
    "recommended_difficulty_max": "198",
    "objective_type": "collect_material",
    "objective_value": "mat_spirit_essence:20",
    "reward_primary_type": "currency_spirit_coin",
    "reward_primary_value": "800",
    "reward_secondary_type": "resource_qi",
    "reward_secondary_value": "2400",
    "reward_item_ref": "none",
    "repeatable": "yes",
    "unlock_condition": "difficulty>=18",
    "note": "재료 파밍"
  },
  {
    "quest_id": "q_daily_006",
    "quest_type": "daily",
    "name_ko": "부적 숙련",
    "world": "daily",
    "recommended_difficulty_min": "40",
    "recommended_difficulty_max": "198",
    "objective_type": "consume_item",
    "objective_value": "tal_guard_02:1",
    "reward_primary_type": "currency_spirit_coin",
    "reward_primary_value": "1400",
    "reward_secondary_type": "currency_rebirth_essence",
    "reward_secondary_value": "8",
    "reward_item_ref": "tal_luck_01",
    "repeatable": "yes",
    "unlock_condition": "difficulty>=40",
    "note": "부적 소모형"
  },
  {
    "quest_id": "q_weekly_001",
    "quest_type": "weekly",
    "name_ko": "주간 도전자",
    "world": "weekly",
    "recommended_difficulty_min": "32",
    "recommended_difficulty_max": "198",
    "objective_type": "kill_boss",
    "objective_value": "8",
    "reward_primary_type": "currency_spirit_coin",
    "reward_primary_value": "6500",
    "reward_secondary_type": "currency_rebirth_essence",
    "reward_secondary_value": "32",
    "reward_item_ref": "pot_tri_03",
    "repeatable": "yes",
    "unlock_condition": "difficulty>=32",
    "note": "주간 핵심"
  },
  {
    "quest_id": "q_weekly_002",
    "quest_type": "weekly",
    "name_ko": "주간 도겁 생존자",
    "world": "weekly",
    "recommended_difficulty_min": "84",
    "recommended_difficulty_max": "198",
    "objective_type": "survive_tribulation",
    "objective_value": "3",
    "reward_primary_type": "currency_spirit_coin",
    "reward_primary_value": "7600",
    "reward_secondary_type": "currency_rebirth_essence",
    "reward_secondary_value": "46",
    "reward_item_ref": "tal_guard_02",
    "repeatable": "yes",
    "unlock_condition": "difficulty>=84",
    "note": "주간 도겁"
  },
  {
    "quest_id": "q_weekly_003",
    "quest_type": "weekly",
    "name_ko": "주간 균열 탐사",
    "world": "weekly",
    "recommended_difficulty_min": "120",
    "recommended_difficulty_max": "198",
    "objective_type": "clear_zone",
    "objective_value": "i_zone_04",
    "reward_primary_type": "currency_spirit_coin",
    "reward_primary_value": "8400",
    "reward_secondary_type": "currency_rebirth_essence",
    "reward_secondary_value": "52",
    "reward_item_ref": "tal_luck_02",
    "repeatable": "yes",
    "unlock_condition": "difficulty>=120",
    "note": "신선계 주간"
  },
  {
    "quest_id": "q_weekly_004",
    "quest_type": "weekly",
    "name_ko": "주간 원초 도전",
    "world": "weekly",
    "recommended_difficulty_min": "183",
    "recommended_difficulty_max": "198",
    "objective_type": "clear_zone",
    "objective_value": "t_zone_03",
    "reward_primary_type": "currency_spirit_coin",
    "reward_primary_value": "9800",
    "reward_secondary_type": "currency_rebirth_essence",
    "reward_secondary_value": "66",
    "reward_item_ref": "pot_tri_03",
    "repeatable": "yes",
    "unlock_condition": "difficulty>=183",
    "note": "진선계 주간"
  },
  {
    "quest_id": "q_side_001",
    "quest_type": "side",
    "name_ko": "영맥 복원",
    "world": "mortal",
    "recommended_difficulty_min": "22",
    "recommended_difficulty_max": "44",
    "objective_type": "spend_spirit_coin",
    "objective_value": "2000",
    "reward_primary_type": "currency_rebirth_essence",
    "reward_primary_value": "8",
    "reward_secondary_type": "resource_qi",
    "reward_secondary_value": "2600",
    "reward_item_ref": "pot_qi_02",
    "repeatable": "no",
    "unlock_condition": "difficulty>=22",
    "note": "서브 퀘스트"
  },
  {
    "quest_id": "q_side_002",
    "quest_type": "side",
    "name_ko": "심마 안정화",
    "world": "immortal",
    "recommended_difficulty_min": "110",
    "recommended_difficulty_max": "150",
    "objective_type": "gain_mind_resist",
    "objective_value": "0.08",
    "reward_primary_type": "currency_rebirth_essence",
    "reward_primary_value": "22",
    "reward_secondary_type": "currency_spirit_coin",
    "reward_secondary_value": "3600",
    "reward_item_ref": "tal_guard_01",
    "repeatable": "no",
    "unlock_condition": "difficulty>=110",
    "note": "저항 성장형"
  },
  {
    "quest_id": "q_side_003",
    "quest_type": "side",
    "name_ko": "윤회의 각인",
    "world": "true",
    "recommended_difficulty_min": "186",
    "recommended_difficulty_max": "198",
    "objective_type": "rebirth_count",
    "objective_value": "3",
    "reward_primary_type": "currency_rebirth_essence",
    "reward_primary_value": "120",
    "reward_secondary_type": "currency_spirit_coin",
    "reward_secondary_value": "9000",
    "reward_item_ref": "tal_luck_02",
    "repeatable": "no",
    "unlock_condition": "difficulty>=186",
    "note": "환생 목표형"
  }
]